README.md
setup.py
smla_info/__init__.py
smla_info/smla_info.py
smla_info.egg-info/PKG-INFO
smla_info.egg-info/SOURCES.txt
smla_info.egg-info/dependency_links.txt
smla_info.egg-info/top_level.txt